pytest_rmsis/__init__.py
pytest_rmsis/plugin.py
pytest_rmsis/rmsis.py
pytest_rmsis/rmsis_schema.py
pytest_rmsis-1.0.0.dist-info/LICENSE
pytest_rmsis-1.0.0.dist-info/METADATA
pytest_rmsis-1.0.0.dist-info/WHEEL
pytest_rmsis-1.0.0.dist-info/entry_points.txt
pytest_rmsis-1.0.0.dist-info/top_level.txt
pytest_rmsis-1.0.0.dist-info/RECORD
