Metadata-Version: 2.1
Name: pytest-rmsis
Version: 1.0.0
Summary: Sycronise pytest results to Jira RMsis
Home-page: https://github.com/helbling-technik-gmbh/pytest-rmsis
Author: Johannes Fischer
Author-email: johannes.fischer@hebling.de
License: MIT
Keywords: py.test pytest rmsis jira
Classifier: Framework :: Pytest
Classifier: Operating System :: Microsoft :: Windows
Classifier: Operating System :: MacOS :: MacOS X
Classifier: Operating System :: POSIX
Classifier: Operating System :: Unix
Classifier: Programming Language :: Python
Classifier: Programming Language :: Python :: 3
Classifier: Programming Language :: Python :: 3.6
Classifier: Programming Language :: Python :: 3.7
Classifier: Programming Language :: Python :: 3.8
Classifier: Programming Language :: Python :: 3.9
License-File: LICENSE
Requires-Dist: pytest (>=5.3.5)
Requires-Dist: sgqlc (>=12.1)
